pdf_gpt4_json/__init__.py
pdf_gpt4_json/cli.py
pdf_gpt4_json/gpt.py
pdf_gpt4_json/main.py
pdf_gpt4_json/util.py
pdf_gpt4_json-0.1.2.dist-info/LICENSE
pdf_gpt4_json-0.1.2.dist-info/METADATA
pdf_gpt4_json-0.1.2.dist-info/WHEEL
pdf_gpt4_json-0.1.2.dist-info/entry_points.txt
pdf_gpt4_json-0.1.2.dist-info/RECORD
