Metadata-Version: 2.1
Name: pdf-gpt4-json
Version: 0.1.2
Summary: Use GTP4-Vision as a better than OCR data extractor
Home-page: https://github.com/maximoguerrero/PDF-GPT4-JSON
License: GPL-3.0-or-later
Author: Maximo G.
Requires-Python: >=3.10,<4.0
Classifier: License :: OSI Approved :: GNU General Public License v3 or later (GPLv3+)
Classifier: Programming Language :: Python :: 3
Classifier: Programming Language :: Python :: 3.10
Classifier: Programming Language :: Python :: 3.11
Classifier: Programming Language :: Python :: 3.12
Requires-Dist: pypdfium2 (>=4.28.0,<5.0.0)
Requires-Dist: requests (>=2.31.0,<3.0.0)
Requires-Dist: split-image (>=2.0.1,<3.0.0)
Requires-Dist: typer (>=0.9.0,<0.10.0)
Project-URL: Repository, https://github.com/maximoguerrero/PDF-GPT4-JSON
